gridfit/__init__.py
gridfit/gridfit.py
gridfit-0.0.1.dist-info/LICENSE
gridfit-0.0.1.dist-info/METADATA
gridfit-0.0.1.dist-info/WHEEL
gridfit-0.0.1.dist-info/top_level.txt
gridfit-0.0.1.dist-info/RECORD
